choba/__init__.py
choba/__main__.py
choba/webdriver.py
choba-1.0.2.data/scripts/choba
choba-1.0.2.dist-info/LICENSE
choba-1.0.2.dist-info/METADATA
choba-1.0.2.dist-info/WHEEL
choba-1.0.2.dist-info/top_level.txt
choba-1.0.2.dist-info/RECORD
